queuemgr/__init__.py
queuemgr/async_process_manager.py
queuemgr/async_process_runner.py
queuemgr/async_simple_api.py
queuemgr/async_simple_queue.py
queuemgr/constants.py
queuemgr/exceptions.py
queuemgr/proc_api.py
queuemgr/proc_config.py
queuemgr/proc_ipc.py
queuemgr/proc_manager.py
queuemgr/proc_manager_bootstrap.py
queuemgr/proc_manager_core.py
queuemgr/process_commands.py
queuemgr/process_config.py
queuemgr/process_context.py
queuemgr/process_core.py
queuemgr/process_manager.py
queuemgr/simple_api.py
queuemgr/core/__init__.py
queuemgr/core/exceptions.py
queuemgr/core/ipc.py
queuemgr/core/ipc_manager.py
queuemgr/core/ipc_operations.py
queuemgr/core/registry.py
queuemgr/core/types.py
queuemgr/examples/__init__.py
queuemgr/examples/async_fastapi_example.py
queuemgr/examples/async_web_example.py
queuemgr/examples/data_analyzer.py
queuemgr/examples/error_handling_job.py
queuemgr/examples/full_app_example.py
queuemgr/examples/large_data_generator.py
queuemgr/examples/large_result_job.py
queuemgr/examples/mcp_adapter_commands.py
queuemgr/examples/proc_manager_example.py
queuemgr/examples/progress_job.py
queuemgr/examples/registry_example.py
queuemgr/examples/result_job.py
queuemgr/examples/service_example.py
queuemgr/examples/simple_job.py
queuemgr/examples/simple_manager_example.py
queuemgr/examples/simple_mcp_example.py
queuemgr/examples/working_mcp_server.py
queuemgr/examples/integration_examples/cli_integration.py
queuemgr/examples/integration_examples/flask_api.py
queuemgr/examples/integration_examples/flask_integration.py
queuemgr/examples/integration_examples/flask_routes.py
queuemgr/examples/integration_examples/systemd_integration.py
queuemgr/examples/jobs/__init__.py
queuemgr/examples/jobs/api_call_job.py
queuemgr/examples/jobs/data_processing_job.py
queuemgr/examples/jobs/file_operation_job.py
queuemgr/jobs/__init__.py
queuemgr/jobs/base.py
queuemgr/jobs/base_core.py
queuemgr/jobs/exceptions.py
queuemgr/jobs/log_capture.py
queuemgr/jobs/registry_job.py
queuemgr-1.0.13.dist-info/licenses/LICENSE
queuemgr-1.0.13.dist-info/METADATA
queuemgr-1.0.13.dist-info/WHEEL
queuemgr-1.0.13.dist-info/entry_points.txt
queuemgr-1.0.13.dist-info/top_level.txt
queuemgr-1.0.13.dist-info/RECORD
