Metadata-Version: 2.4
Name: queuemgr
Version: 1.0.13
Summary: Full-featured job queue system with multiprocessing support for Linux
Home-page: https://github.com/vasilyvz/queuemgr
Author: Vasiliy Zdanovskiy
Author-email: Vasiliy Zdanovskiy <vasilyvz@gmail.com>
License: MIT
Project-URL: Homepage, https://github.com/vasilyvz/queuemgr
Project-URL: Repository, https://github.com/vasilyvz/queuemgr
Project-URL: Documentation, https://github.com/vasilyvz/queuemgr#readme
Project-URL: Bug Tracker, https://github.com/vasilyvz/queuemgr/issues
Keywords: job-queue,multiprocessing,task-scheduler,linux,systemd
Classifier: Development Status :: 5 - Production/Stable
Classifier: Intended Audience :: Developers
Classifier: Intended Audience :: System Administrators
Classifier: License :: OSI Approved :: MIT License
Classifier: Operating System :: POSIX :: Linux
Classifier: Programming Language :: Python :: 3
Classifier: Programming Language :: Python :: 3.10
Classifier: Programming Language :: Python :: 3.11
Classifier: Programming Language :: Python :: 3.12
Classifier: Topic :: Software Development :: Libraries :: Python Modules
Classifier: Topic :: System :: Distributed Computing
Classifier: Topic :: System :: Systems Administration
Classifier: Topic :: Internet :: WWW/HTTP :: Dynamic Content
Classifier: Topic :: Scientific/Engineering
Requires-Python: >=3.10
License-File: LICENSE
Provides-Extra: dev
Requires-Dist: pytest>=7.0.0; extra == "dev"
Requires-Dist: pytest-cov>=4.0.0; extra == "dev"
Requires-Dist: black>=23.0.0; extra == "dev"
Requires-Dist: flake8>=6.0.0; extra == "dev"
Requires-Dist: mypy>=1.0.0; extra == "dev"
Provides-Extra: web
Requires-Dist: flask>=2.0.0; extra == "web"
Provides-Extra: examples
Requires-Dist: requests>=2.25.0; extra == "examples"
Dynamic: author
Dynamic: home-page
Dynamic: license-file
Dynamic: requires-python
